{"features": [{"geometry": {"coordinates": [[[1, 1, 0.0], [1, 1, 0.0], [1, 1, 0.0], [1, 1, 0.0]]], "type": "Polygon"}, "properties": {"object_imcoords": "143.2691536477335,618.6412334344893,173.30412070186537,625.5184037899205,167.9719446577074,648.8058495759099,137.93697760357554,641.9286792204787", "object_angle": 6.058093366485833, "building_imcoords": "EMPTY", "road_imcoords": "EMPTY", "image_id": "OBJ02596_PS3_K3_NIA0124.png", "ingest_time": "2020-08-27T01:52:33.288673Z", "type_id": "4", "type_name": "military aircraft"}, "type": "Feature"}], "type": "FeatureCollection"}