{"features": [{"geometry": {"coordinates": [[[1, 1, 0.0], [1, 1, 0.0], [1, 1, 0.0], [1, 1, 0.0]]], "type": "Polygon"}, "properties": {"object_imcoords": "434.43004299948757,498.5314955567402,529.6725889966066,465.80384496027796,561.515720010542,558.4723016021022,466.27317401342304,591.1999521985645", "object_angle": 6.614168938685991, "building_imcoords": "EMPTY", "road_imcoords": "EMPTY", "image_id": "OBJ05528_PS3_K3A_NIA0352.png", "ingest_time": "2020-09-10T05:16:43.630166Z", "type_id": "4", "type_name": "military aircraft"}, "type": "Feature"}, {"geometry": {"coordinates": [[[1, 1, 0.0], [1, 1, 0.0], [1, 1, 0.0], [1, 1, 0.0]]], "type": "Polygon"}, "properties": {"object_imcoords": "636.2397624075918,206.35477458040805,643.4258914350548,203.94302637506982,647.7469403029525,216.81817421594116,640.5608112754894,219.22992242127938", "object_angle": 0.3237995841256943, "building_imcoords": "EMPTY", "road_imcoords": "EMPTY", "image_id": "OBJ05528_PS3_K3A_NIA0352.png", "ingest_time": "2020-09-10T05:16:43.630166Z", "type_id": "5", "type_name": "small car"}, "type": "Feature"}], "type": "FeatureCollection"}